lenders_sentry_utils/__init__.py
lenders_sentry_utils/transport.py
lenders_sentry_utils/utils.py
lenders_sentry_utils-0.2.dist-info/LICENSE
lenders_sentry_utils-0.2.dist-info/METADATA
lenders_sentry_utils-0.2.dist-info/WHEEL
lenders_sentry_utils-0.2.dist-info/top_level.txt
lenders_sentry_utils-0.2.dist-info/RECORD
