Metadata-Version: 2.1
Name: lenders-sentry-utils
Version: 0.2
Summary: A small set of utilities for configuring sentry & modifying normal sentry_sdk functionality
Home-page: https://github.com/Lenders-Cooperative/sentry-utils
Author: Levi Anderson
License: UNKNOWN
Platform: UNKNOWN
Classifier: Programming Language :: Python :: 3
Classifier: License :: OSI Approved :: BSD License
Classifier: Operating System :: OS Independent
Requires-Python: >=3.6
License-File: LICENSE
Requires-Dist: sentry-sdk (>=0.16)
Requires-Dist: django-environ (>=0.4.5)
Requires-Dist: celery (>=4.4.3)
Requires-Dist: redis (>=3.3.11)
